python_vcon-0.6.0.data/data/vcon/pip_package_list.txt
python_vcon-0.6.0.data/scripts/vcon
vcon/__init__.py
vcon/accessors.py
vcon/cli.py
vcon/pydantic_utils.py
vcon/security.py
vcon/utils.py
vcon/filter_plugins/__init__.py
vcon/filter_plugins/create_amended.py
vcon/filter_plugins/decryptfilter.py
vcon/filter_plugins/deepgram.py
vcon/filter_plugins/encryptfilter.py
vcon/filter_plugins/jq_redaction.py
vcon/filter_plugins/openai.py
vcon/filter_plugins/redact_pii.py
vcon/filter_plugins/signfilter.py
vcon/filter_plugins/verifyfilter.py
vcon/filter_plugins/whisper.py
vcon/filter_plugins/impl/create_amended.py
vcon/filter_plugins/impl/decrypt_filter_plugin.py
vcon/filter_plugins/impl/deepgram.py
vcon/filter_plugins/impl/encrypt_filter_plugin.py
vcon/filter_plugins/impl/jq_redaction.py
vcon/filter_plugins/impl/openai.py
vcon/filter_plugins/impl/redact_pii.py
vcon/filter_plugins/impl/sign_filter_plugin.py
vcon/filter_plugins/impl/verify_filter_plugin.py
vcon/filter_plugins/impl/whisper.py
vcon/filter_plugins_addons/__init__.py
python_vcon-0.6.0.dist-info/LICENSE
python_vcon-0.6.0.dist-info/METADATA
python_vcon-0.6.0.dist-info/WHEEL
python_vcon-0.6.0.dist-info/top_level.txt
python_vcon-0.6.0.dist-info/RECORD
