Metadata-Version: 2.1
Name: python-vcon
Version: 0.6.0
Summary: vCon conversational data container manipulation package
Home-page: http://github.com/py-vcon/py-vcon
Author: Dan Petrie
Author-email: dan.vcon@sipez.com
License: MIT
Requires-Python: >=3.8
License-File: LICENSE
Requires-Dist: deepgram-sdk <3
Requires-Dist: cbor2
Requires-Dist: cryptography >=37
Requires-Dist: hsslms
Requires-Dist: openai
Requires-Dist: pydantic
Requires-Dist: pyjq
Requires-Dist: python-jose !=3.4.*
Requires-Dist: python-dateutil
Requires-Dist: pytz
Requires-Dist: regex
Requires-Dist: requests
Requires-Dist: sox
Requires-Dist: tenacity
Requires-Dist: uuid6
Requires-Dist: python-json-logger
Requires-Dist: python-multipart
Requires-Dist: ffmpeg-python
Requires-Dist: more-itertools
Requires-Dist: tqdm
Requires-Dist: transformers
Requires-Dist: whisper
Requires-Dist: numpy <1.25
Requires-Dist: torch >=2.1
Requires-Dist: stable-ts >2
Requires-Dist: pandas
Requires-Dist: tensorflow
Requires-Dist: scikit-learn
Requires-Dist: dataprofiler
